darabonba_base_python/__init__.py
darabonba_base_python/client.py
darabonba_base_python-0.0.1.dist-info/METADATA
darabonba_base_python-0.0.1.dist-info/WHEEL
darabonba_base_python-0.0.1.dist-info/RECORD
